{
  "metadata": {
    "name": "Balam Kin",
    "designation": "\u00c1rea de Protecci\u00f3n de Flora y Fauna",
    "designation_type": "National",
    "iucn_category": "VI",
    "status": "Designated",
    "status_year": 2023,
    "governance": "Federal or national ministry or agency",
    "management_authority": "National Commission of Natural Protected Areas",
    "reported_area_km2": 1156.582475,
    "country": "MEX",
    "extracted_at": "2026-01-02T13:39:33.486189"
  },
  "geometry": {
    "centroid": [
      -89.83244377826043,
      19.00803103009609
    ],
    "bounds": [
      [
        -90.17560239939284,
        18.897652467591474
      ],
      [
        -89.58272924196767,
        18.897652467591474
      ],
      [
        -89.58272924196767,
        19.20471504738365
      ],
      [
        -90.17560239939284,
        19.20471504738365
      ],
      [
        -90.17560239939284,
        18.897652467591474
      ]
    ]
  },
  "datasets": {
    "population": {
      "year_2020": {
        "population": 48.04658550234931
      }
    },
    "elevation": {
      "elevation_max": 286,
      "elevation_mean": 148.94800173877428,
      "elevation_min": 34
    },
    "land_cover": {
      "classes": {
        "Tree cover": {
          "class_id": 10,
          "area_km2": 1113.4
        },
        "Shrubland": {
          "class_id": 20,
          "area_km2": 4.34
        },
        "Grassland": {
          "class_id": 30,
          "area_km2": 37.17
        },
        "Cropland": {
          "class_id": 40,
          "area_km2": 0.05
        },
        "Herbaceous wetland": {
          "class_id": 90,
          "area_km2": 0.0
        }
      }
    },
    "forest": {
      "tree_cover_2000_percent": 94.65285037393956,
      "total_loss_km2": 20.63,
      "loss_by_year": {
        "2001": 0.1,
        "2002": 0.07,
        "2003": 0.31,
        "2004": 0.34,
        "2005": 0.15,
        "2006": 0.16,
        "2007": 0.29,
        "2008": 0.35,
        "2009": 2.86,
        "2010": 0.18,
        "2011": 0.17,
        "2012": 0.59,
        "2013": 3.01,
        "2014": 0.23,
        "2015": 0.47,
        "2016": 0.25,
        "2017": 1.17,
        "2018": 0.08,
        "2019": 2.46,
        "2020": 2.39,
        "2021": 0.95,
        "2022": 1.92,
        "2023": 2.15
      }
    },
    "climate": {
      "annual_precipitation_mm": 1386.5651617526614,
      "mean_max_temp_c": 32.60936646874147,
      "mean_min_temp_c": 20.099702259077254
    },
    "vegetation": {
      "NDVI_max": 0.8411869565217392,
      "NDVI_mean": 0.7821322556199181,
      "NDVI_min": 0.6604652173913044
    },
    "night_lights": {
      "avg_rad_max": 0.2916666567325592,
      "avg_rad_mean": 0.2424323014761713
    },
    "fire": {
      "burned_area_km2_by_year": {
        "2019": 3.11,
        "2020": 2.04,
        "2021": 0.0,
        "2022": 0.21,
        "2023": 0.0
      }
    },
    "biodiversity": {
      "ecoregions": [
        "Yucat\u00e1n moist forests"
      ],
      "biomes": [
        "Tropical & Subtropical Moist Broadleaf Forests"
      ]
    },
    "human_modification": {
      "gHM_max": 0.2096109241247177,
      "gHM_mean": 0.037352907978844836
    },
    "water_stress": {
      "source": "WRI Aqueduct Water Risk Atlas V4",
      "resolution": "Sub-basin (HydroBASINS level 6)",
      "data_available": true,
      "sub_basins_count": 3,
      "baseline_water_stress": 0.0813,
      "baseline_water_stress_category": "Low (<10%)",
      "drought_risk": 0.5497,
      "drought_risk_category": "Medium",
      "interpretation": {
        "BWS": "Ratio of total water withdrawals to available supply. Protected areas often show 'No Data' due to minimal human water use.",
        "DRR": "Probability-weighted drought severity (0-1 scale)."
      },
      "note": null,
      "extracted_at": "2026-01-03T10:30:36.784729"
    },
    "gedi_biomass": {
      "source": "NASA GEDI L4A (Aboveground Biomass Density)",
      "resolution": "25m footprints",
      "data_available": true,
      "gedi_images_used": 118,
      "agbd_mean_mg_ha": 41.03,
      "agbd_max_mg_ha": 3475.72,
      "agbd_std_mg_ha": 114.82,
      "sampled_pixels": 332934,
      "anp_area_ha": 212764.0,
      "total_carbon_estimate_mt": 8730.0,
      "interpretation": {
        "agbd": "Aboveground Biomass Density in Megagrams (tonnes) per hectare",
        "total_carbon": "Rough estimate of total aboveground carbon stock in megatonnes"
      },
      "extracted_at": "2026-01-03T10:57:03.407442"
    }
  },
  "external_data": {
    "gbif_species": {
      "source": "GBIF (Global Biodiversity Information Facility)",
      "query_date": "2026-01-02T22:56:29.553582",
      "total_occurrences": 8171,
      "unique_species": 97,
      "bounding_box": {
        "minLon": -90.17560239939284,
        "maxLon": -89.58272924196767,
        "minLat": 18.8976524675915,
        "maxLat": 19.204715047383623
      },
      "species_by_class": {
        "Aves": 69,
        "Insecta": 3,
        "Mammalia": 5,
        "Squamata": 3,
        "Crocodylia": 1,
        "Magnoliopsida": 13,
        "Liliopsida": 3
      },
      "top_species": [
        {
          "scientific_name": "Guaiacum sanctum",
          "kingdom": "Plantae",
          "phylum": "Tracheophyta",
          "class": "Magnoliopsida",
          "order": "Zygophyllales",
          "family": "Zygophyllaceae",
          "genus": "Guaiacum",
          "taxon_key": 3189908,
          "occurrences": 713
        },
        {
          "scientific_name": "Mimosa bahamensis",
          "kingdom": "Plantae",
          "phylum": "Tracheophyta",
          "class": "Magnoliopsida",
          "order": "Fabales",
          "family": "Fabaceae",
          "genus": "Mimosa",
          "taxon_key": 2970059,
          "occurrences": 236
        },
        {
          "scientific_name": "Lonchocarpus yucatanensis",
          "kingdom": "Plantae",
          "phylum": "Tracheophyta",
          "class": "Magnoliopsida",
          "order": "Fabales",
          "family": "Fabaceae",
          "genus": "Lonchocarpus",
          "taxon_key": 2969081,
          "occurrences": 141
        },
        {
          "scientific_name": "Bursera simaruba",
          "kingdom": "Plantae",
          "phylum": "Tracheophyta",
          "class": "Magnoliopsida",
          "order": "Sapindales",
          "family": "Burseraceae",
          "genus": "Bursera",
          "taxon_key": 3190450,
          "occurrences": 114
        },
        {
          "scientific_name": "Cordia dodecandra",
          "kingdom": "Plantae",
          "phylum": "Tracheophyta",
          "class": "Magnoliopsida",
          "order": "Boraginales",
          "family": "Cordiaceae",
          "genus": "Cordia",
          "taxon_key": 5662394,
          "occurrences": 113
        },
        {
          "scientific_name": "Vitex gaumeri",
          "kingdom": "Plantae",
          "phylum": "Tracheophyta",
          "class": "Magnoliopsida",
          "order": "Lamiales",
          "family": "Lamiaceae",
          "genus": "Vitex",
          "taxon_key": 3905536,
          "occurrences": 96
        },
        {
          "scientific_name": "Amazona albifrons",
          "kingdom": "Animalia",
          "phylum": "Chordata",
          "class": "Aves",
          "order": "Psittaciformes",
          "family": "Psittacidae",
          "genus": "Amazona",
          "taxon_key": 2479618,
          "occurrences": 62
        },
        {
          "scientific_name": "Melanerpes aurifrons",
          "kingdom": "Animalia",
          "phylum": "Chordata",
          "class": "Aves",
          "order": "Piciformes",
          "family": "Picidae",
          "genus": "Melanerpes",
          "taxon_key": 2478081,
          "occurrences": 49
        },
        {
          "scientific_name": "Psilorhinus morio",
          "kingdom": "Animalia",
          "phylum": "Chordata",
          "class": "Aves",
          "order": "Passeriformes",
          "family": "Corvidae",
          "genus": "Psilorhinus",
          "taxon_key": 5229495,
          "occurrences": 37
        },
        {
          "scientific_name": "Attila spadiceus",
          "kingdom": "Animalia",
          "phylum": "Chordata",
          "class": "Aves",
          "order": "Passeriformes",
          "family": "Tyrannidae",
          "genus": "Attila",
          "taxon_key": 2483629,
          "occurrences": 31
        },
        {
          "scientific_name": "Setophaga magnolia",
          "kingdom": "Animalia",
          "phylum": "Chordata",
          "class": "Aves",
          "order": "Passeriformes",
          "family": "Parulidae",
          "genus": "Setophaga",
          "taxon_key": 6093209,
          "occurrences": 31
        },
        {
          "scientific_name": "Tabebuia rosea",
          "kingdom": "Plantae",
          "phylum": "Tracheophyta",
          "class": "Magnoliopsida",
          "order": "Lamiales",
          "family": "Bignoniaceae",
          "genus": "Tabebuia",
          "taxon_key": 3172537,
          "occurrences": 28
        },
        {
          "scientific_name": "Cyanocorax yucatanicus",
          "kingdom": "Animalia",
          "phylum": "Chordata",
          "class": "Aves",
          "order": "Passeriformes",
          "family": "Corvidae",
          "genus": "Cyanocorax",
          "taxon_key": 2482574,
          "occurrences": 27
        },
        {
          "scientific_name": "Astronium graveolens",
          "kingdom": "Plantae",
          "phylum": "Tracheophyta",
          "class": "Magnoliopsida",
          "order": "Sapindales",
          "family": "Anacardiaceae",
          "genus": "Astronium",
          "taxon_key": 7321588,
          "occurrences": 27
        },
        {
          "scientific_name": "Plumeria obtusa",
          "kingdom": "Plantae",
          "phylum": "Tracheophyta",
          "class": "Magnoliopsida",
          "order": "Gentianales",
          "family": "Apocynaceae",
          "genus": "Plumeria",
          "taxon_key": 3169677,
          "occurrences": 26
        },
        {
          "scientific_name": "Patagioenas flavirostris",
          "kingdom": "Animalia",
          "phylum": "Chordata",
          "class": "Aves",
          "order": "Columbiformes",
          "family": "Columbidae",
          "genus": "Patagioenas",
          "taxon_key": 2495303,
          "occurrences": 24
        },
        {
          "scientific_name": "Cascabela gaumeri",
          "kingdom": "Plantae",
          "phylum": "Tracheophyta",
          "class": "Magnoliopsida",
          "order": "Gentianales",
          "family": "Apocynaceae",
          "genus": "Cascabela",
          "taxon_key": 3618725,
          "occurrences": 24
        },
        {
          "scientific_name": "Trogon melanocephalus",
          "kingdom": "Animalia",
          "phylum": "Chordata",
          "class": "Aves",
          "order": "Trogoniformes",
          "family": "Trogonidae",
          "genus": "Trogon",
          "taxon_key": 2496699,
          "occurrences": 23
        },
        {
          "scientific_name": "Leptotila verreauxi",
          "kingdom": "Animalia",
          "phylum": "Chordata",
          "class": "Aves",
          "order": "Columbiformes",
          "family": "Columbidae",
          "genus": "Leptotila",
          "taxon_key": 2496060,
          "occurrences": 23
        },
        {
          "scientific_name": "Glaucidium brasilianum",
          "kingdom": "Animalia",
          "phylum": "Chordata",
          "class": "Aves",
          "order": "Strigiformes",
          "family": "Strigidae",
          "genus": "Glaucidium",
          "taxon_key": 5232118,
          "occurrences": 22
        },
        {
          "scientific_name": "Trogon caligatus",
          "kingdom": "Animalia",
          "phylum": "Chordata",
          "class": "Aves",
          "order": "Trogoniformes",
          "family": "Trogonidae",
          "genus": "Trogon",
          "taxon_key": 5788446,
          "occurrences": 22
        },
        {
          "scientific_name": "Vireo griseus",
          "kingdom": "Animalia",
          "phylum": "Chordata",
          "class": "Aves",
          "order": "Passeriformes",
          "family": "Vireonidae",
          "genus": "Vireo",
          "taxon_key": 2487413,
          "occurrences": 20
        },
        {
          "scientific_name": "Rupornis magnirostris",
          "kingdom": "Animalia",
          "phylum": "Chordata",
          "class": "Aves",
          "order": "Accipitriformes",
          "family": "Accipitridae",
          "genus": "Rupornis",
          "taxon_key": 5844398,
          "occurrences": 18
        },
        {
          "scientific_name": "Uropsila leucogastra",
          "kingdom": "Animalia",
          "phylum": "Chordata",
          "class": "Aves",
          "order": "Passeriformes",
          "family": "Troglodytidae",
          "genus": "Uropsila",
          "taxon_key": 2493898,
          "occurrences": 17
        },
        {
          "scientific_name": "Zenaida asiatica",
          "kingdom": "Animalia",
          "phylum": "Chordata",
          "class": "Aves",
          "order": "Columbiformes",
          "family": "Columbidae",
          "genus": "Zenaida",
          "taxon_key": 2495370,
          "occurrences": 16
        },
        {
          "scientific_name": "Xiphorhynchus flavigaster",
          "kingdom": "Animalia",
          "phylum": "Chordata",
          "class": "Aves",
          "order": "Passeriformes",
          "family": "Furnariidae",
          "genus": "Xiphorhynchus",
          "taxon_key": 5230178,
          "occurrences": 16
        },
        {
          "scientific_name": "Crypturellus cinnamomeus",
          "kingdom": "Animalia",
          "phylum": "Chordata",
          "class": "Aves",
          "order": "Tinamiformes",
          "family": "Tinamidae",
          "genus": "Crypturellus",
          "taxon_key": 2477493,
          "occurrences": 15
        },
        {
          "scientific_name": "Campephilus guatemalensis",
          "kingdom": "Animalia",
          "phylum": "Chordata",
          "class": "Aves",
          "order": "Piciformes",
          "family": "Picidae",
          "genus": "Campephilus",
          "taxon_key": 2478580,
          "occurrences": 11
        },
        {
          "scientific_name": "Havardia albicans",
          "kingdom": "Plantae",
          "phylum": "Tracheophyta",
          "class": "Magnoliopsida",
          "order": "Fabales",
          "family": "Fabaceae",
          "genus": "Havardia",
          "taxon_key": 2933859,
          "occurrences": 11
        },
        {
          "scientific_name": "Arremonops chloronotus",
          "kingdom": "Animalia",
          "phylum": "Chordata",
          "class": "Aves",
          "order": "Passeriformes",
          "family": "Passerellidae",
          "genus": "Arremonops",
          "taxon_key": 2491042,
          "occurrences": 10
        },
        {
          "scientific_name": "Ortalis vetula",
          "kingdom": "Animalia",
          "phylum": "Chordata",
          "class": "Aves",
          "order": "Galliformes",
          "family": "Cracidae",
          "genus": "Ortalis",
          "taxon_key": 5229429,
          "occurrences": 10
        },
        {
          "scientific_name": "Piaya cayana",
          "kingdom": "Animalia",
          "phylum": "Chordata",
          "class": "Aves",
          "order": "Cuculiformes",
          "family": "Cuculidae",
          "genus": "Piaya",
          "taxon_key": 2496432,
          "occurrences": 10
        },
        {
          "scientific_name": "Momotus lessonii",
          "kingdom": "Animalia",
          "phylum": "Chordata",
          "class": "Aves",
          "order": "Coraciiformes",
          "family": "Momotidae",
          "genus": "Momotus",
          "taxon_key": 6100745,
          "occurrences": 10
        },
        {
          "scientific_name": "Ramphastos sulfuratus",
          "kingdom": "Animalia",
          "phylum": "Chordata",
          "class": "Aves",
          "order": "Piciformes",
          "family": "Ramphastidae",
          "genus": "Ramphastos",
          "taxon_key": 2478771,
          "occurrences": 10
        },
        {
          "scientific_name": "Herpetotheres cachinnans",
          "kingdom": "Animalia",
          "phylum": "Chordata",
          "class": "Aves",
          "order": "Falconiformes",
          "family": "Falconidae",
          "genus": "Herpetotheres",
          "taxon_key": 2481071,
          "occurrences": 10
        },
        {
          "scientific_name": "Amazilia yucatanensis",
          "kingdom": "Animalia",
          "phylum": "Chordata",
          "class": "Aves",
          "order": "Apodiformes",
          "family": "Trochilidae",
          "genus": "Amazilia",
          "taxon_key": 2476483,
          "occurrences": 9
        },
        {
          "scientific_name": "Pitangus sulphuratus",
          "kingdom": "Animalia",
          "phylum": "Chordata",
          "class": "Aves",
          "order": "Passeriformes",
          "family": "Tyrannidae",
          "genus": "Pitangus",
          "taxon_key": 2482755,
          "occurrences": 9
        },
        {
          "scientific_name": "Mniotilta varia",
          "kingdom": "Animalia",
          "phylum": "Chordata",
          "class": "Aves",
          "order": "Passeriformes",
          "family": "Parulidae",
          "genus": "Mniotilta",
          "taxon_key": 2489613,
          "occurrences": 9
        },
        {
          "scientific_name": "Myiozetetes similis",
          "kingdom": "Animalia",
          "phylum": "Chordata",
          "class": "Aves",
          "order": "Passeriformes",
          "family": "Tyrannidae",
          "genus": "Myiozetetes",
          "taxon_key": 2482913,
          "occurrences": 9
        },
        {
          "scientific_name": "Turdus grayi",
          "kingdom": "Animalia",
          "phylum": "Chordata",
          "class": "Aves",
          "order": "Passeriformes",
          "family": "Turdidae",
          "genus": "Turdus",
          "taxon_key": 2490716,
          "occurrences": 9
        },
        {
          "scientific_name": "Thryothorus ludovicianus",
          "kingdom": "Animalia",
          "phylum": "Chordata",
          "class": "Aves",
          "order": "Passeriformes",
          "family": "Troglodytidae",
          "genus": "Thryothorus",
          "taxon_key": 2493801,
          "occurrences": 9
        },
        {
          "scientific_name": "Byrsonima crassifolia",
          "kingdom": "Plantae",
          "phylum": "Tracheophyta",
          "class": "Magnoliopsida",
          "order": "Malpighiales",
          "family": "Malpighiaceae",
          "genus": "Byrsonima",
          "taxon_key": 3191361,
          "occurrences": 9
        },
        {
          "scientific_name": "Leptotila jamaicensis",
          "kingdom": "Animalia",
          "phylum": "Chordata",
          "class": "Aves",
          "order": "Columbiformes",
          "family": "Columbidae",
          "genus": "Leptotila",
          "taxon_key": 2496098,
          "occurrences": 8
        },
        {
          "scientific_name": "Oncostoma cinereigulare",
          "kingdom": "Animalia",
          "phylum": "Chordata",
          "class": "Aves",
          "order": "Passeriformes",
          "family": "Tyrannidae",
          "genus": "Oncostoma",
          "taxon_key": 5229773,
          "occurrences": 7
        },
        {
          "scientific_name": "Saltator atriceps",
          "kingdom": "Animalia",
          "phylum": "Chordata",
          "class": "Aves",
          "order": "Passeriformes",
          "family": "Thraupidae",
          "genus": "Saltator",
          "taxon_key": 5230896,
          "occurrences": 7
        },
        {
          "scientific_name": "Tolmomyias sulphurescens",
          "kingdom": "Animalia",
          "phylum": "Chordata",
          "class": "Aves",
          "order": "Passeriformes",
          "family": "Tyrannidae",
          "genus": "Tolmomyias",
          "taxon_key": 2482882,
          "occurrences": 7
        },
        {
          "scientific_name": "Sceloporus chrysostictus",
          "kingdom": "Animalia",
          "phylum": "Chordata",
          "class": "Squamata",
          "order": null,
          "family": "Phrynosomatidae",
          "genus": "Sceloporus",
          "taxon_key": 2451284,
          "occurrences": 7
        },
        {
          "scientific_name": "Dives dives",
          "kingdom": "Animalia",
          "phylum": "Chordata",
          "class": "Aves",
          "order": "Passeriformes",
          "family": "Icteridae",
          "genus": "Dives",
          "taxon_key": 2484434,
          "occurrences": 6
        },
        {
          "scientific_name": "Aechmea bracteata",
          "kingdom": "Plantae",
          "phylum": "Tracheophyta",
          "class": "Liliopsida",
          "order": "Poales",
          "family": "Bromeliaceae",
          "genus": "Aechmea",
          "taxon_key": 2697927,
          "occurrences": 6
        },
        {
          "scientific_name": "Sarcoramphus papa",
          "kingdom": "Animalia",
          "phylum": "Chordata",
          "class": "Aves",
          "order": "Accipitriformes",
          "family": "Cathartidae",
          "genus": "Sarcoramphus",
          "taxon_key": 2481923,
          "occurrences": 1
        }
      ]
    },
    "iucn_threatened": {
      "source": "GBIF IUCN Red List data",
      "critically_endangered": [
        "Cedrela odorata"
      ],
      "endangered": [
        "Alouatta pigra",
        "Amazona oratrix",
        "Swietenia macrophylla",
        "Terminalia buceras"
      ],
      "vulnerable": [
        "Beaucarnea pliabilis"
      ],
      "total_threatened": 6
    },
    "simec_nom059": {
      "error": "ANP not found in SIMEC data"
    },
    "nom059_enciclovida": {
      "source": "NOM-059-SEMARNAT (via Enciclovida)",
      "endangered_P": [],
      "threatened_A": [],
      "special_protection_Pr": [],
      "probably_extinct_E": [],
      "total_nom059": 0,
      "species_checked": 50
    },
    "inegi_census": {
      "source": "INEGI Censo 2020 (ITER)",
      "localities_in_area": 6,
      "total_population": 23,
      "female_population": 3,
      "male_population": 4,
      "female_percent": 13.0,
      "indigenous_speakers_3plus": 1,
      "indigenous_speakers_5plus": 1,
      "indigenous_households_pop": 1,
      "afromexican_population": 0,
      "population_60plus": 0,
      "economically_active": 6,
      "employed": 6,
      "unemployed": 0,
      "illiterate_15plus": 2,
      "no_schooling_15plus": 1,
      "post_basic_education_18plus": 0,
      "avg_schooling_years": 5.2,
      "no_health_services": 6,
      "with_health_services": 1,
      "with_disability": 0,
      "homes_dirt_floor": 4,
      "homes_no_electricity": 2,
      "homes_no_water": 4,
      "homes_no_drainage": 3,
      "homes_no_services": 2,
      "total_households": 4,
      "female_headed_households": 1,
      "sample_localities": [
        "El Ed\u00e9n",
        "X-Tok",
        "Los Gallitos",
        "Los Platanales",
        "Ninguno",
        "El Campito"
      ]
    },
    "extracted_at": "2026-01-02T22:57:32.571296",
    "coneval_irs": {
      "source": "CONEVAL IRS 2020 (Indice de Rezago Social)",
      "data_available": true,
      "municipalities_count": 3,
      "total_population": 133777,
      "irs_weighted_mean": -0.0834,
      "irs_predominant_category": "Bajo",
      "irs_category_distribution": {
        "Bajo": 2,
        "Medio": 1
      },
      "municipalities": [
        {
          "name": "Esc\u00e1rcega",
          "state": "Campeche",
          "population": 59923,
          "irs_index": -0.3795,
          "irs_category": "Bajo",
          "national_rank": 1404
        },
        {
          "name": "Hopelch\u00e9n",
          "state": "Campeche",
          "population": 42140,
          "irs_index": 0.0362,
          "irs_category": "Bajo",
          "national_rank": 986
        },
        {
          "name": "Calakmul",
          "state": "Campeche",
          "population": 31714,
          "irs_index": 0.3171,
          "irs_category": "Medio",
          "national_rank": 727
        }
      ],
      "interpretation": {
        "irs_index": "Social Lag Index: negative values = low lag (better conditions), positive = high lag (worse conditions)",
        "categories": "Muy bajo (best) \u2192 Bajo \u2192 Medio \u2192 Alto \u2192 Muy alto (worst)",
        "weighted_mean": "Population-weighted average across all municipalities intersecting ANP"
      },
      "extracted_at": "2026-01-03T11:15:17.578684"
    },
    "inaturalist": {
      "source": "iNaturalist (Naturalista)",
      "data_available": true,
      "total_observations": 80,
      "unique_species": 67,
      "species_by_group": {
        "Aves": 40,
        "Reptilia": 6,
        "Mammalia": 8,
        "Plantae": 9,
        "Insecta": 3,
        "Arachnida": 1
      },
      "top_species": [
        {
          "scientific_name": "Eumomota superciliosa",
          "common_name": "Momoto Cejas Azules",
          "iconic_taxon": "Aves",
          "observations": 2,
          "taxon_id": 2168
        },
        {
          "scientific_name": "Herpetotheres cachinnans",
          "common_name": "Halc\u00f3n guaco",
          "iconic_taxon": "Aves",
          "observations": 2,
          "taxon_id": 4719
        },
        {
          "scientific_name": "Sarcoramphus papa",
          "common_name": "Zopilote rey",
          "iconic_taxon": "Aves",
          "observations": 2,
          "taxon_id": 4763
        },
        {
          "scientific_name": "Egretta caerulea",
          "common_name": "Garceta Azul",
          "iconic_taxon": "Aves",
          "observations": 2,
          "taxon_id": 4937
        },
        {
          "scientific_name": "Chondrohierax uncinatus",
          "common_name": "Gavil\u00e1n Pico de Gancho",
          "iconic_taxon": "Aves",
          "observations": 2,
          "taxon_id": 5329
        },
        {
          "scientific_name": "Cyanocompsa parellina",
          "common_name": "Color\u00edn azulnegro",
          "iconic_taxon": "Aves",
          "observations": 2,
          "taxon_id": 9519
        },
        {
          "scientific_name": "Myiozetetes similis",
          "common_name": "Luisito Com\u00fan",
          "iconic_taxon": "Aves",
          "observations": 2,
          "taxon_id": 16842
        },
        {
          "scientific_name": "Campephilus guatemalensis",
          "common_name": "Carpintero Pico Plateado",
          "iconic_taxon": "Aves",
          "observations": 2,
          "taxon_id": 18291
        },
        {
          "scientific_name": "Crocodylus moreletii",
          "common_name": "Cocodrilo de pantano",
          "iconic_taxon": "Reptilia",
          "observations": 2,
          "taxon_id": 26074
        },
        {
          "scientific_name": "Urocyon cinereoargenteus",
          "common_name": "Zorra gris",
          "iconic_taxon": "Mammalia",
          "observations": 2,
          "taxon_id": 42076
        },
        {
          "scientific_name": "Tapirus bairdii",
          "common_name": "Tapir Centroamericano",
          "iconic_taxon": "Mammalia",
          "observations": 2,
          "taxon_id": 43355
        },
        {
          "scientific_name": "Psarocolius montezuma",
          "common_name": "Orop\u00e9ndola de Moctezuma",
          "iconic_taxon": "Aves",
          "observations": 2,
          "taxon_id": 68047
        },
        {
          "scientific_name": "Bursera simaruba",
          "common_name": "Palo mulato",
          "iconic_taxon": "Plantae",
          "observations": 2,
          "taxon_id": 130734
        },
        {
          "scientific_name": "Meleagris ocellata",
          "common_name": "Pavo o guajolote ocelado",
          "iconic_taxon": "Aves",
          "observations": 1,
          "taxon_id": 913
        },
        {
          "scientific_name": "Colinus nigrogularis",
          "common_name": "Codorniz yucateca",
          "iconic_taxon": "Aves",
          "observations": 1,
          "taxon_id": 1321
        },
        {
          "scientific_name": "Crotophaga sulcirostris",
          "common_name": "Garrapatero pijuy",
          "iconic_taxon": "Aves",
          "observations": 1,
          "taxon_id": 1972
        },
        {
          "scientific_name": "Crax rubra",
          "common_name": "Pav\u00f3n Grande",
          "iconic_taxon": "Aves",
          "observations": 1,
          "taxon_id": 2052
        },
        {
          "scientific_name": "Megaceryle torquata",
          "common_name": "Mart\u00edn pescador de collar",
          "iconic_taxon": "Aves",
          "observations": 1,
          "taxon_id": 2552
        },
        {
          "scientific_name": "Zenaida asiatica",
          "common_name": "Paloma Alas Blancas",
          "iconic_taxon": "Aves",
          "observations": 1,
          "taxon_id": 3460
        },
        {
          "scientific_name": "Micrastur semitorquatus",
          "common_name": "Halc\u00f3n Selv\u00e1tico de Collar",
          "iconic_taxon": "Aves",
          "observations": 1,
          "taxon_id": 4698
        },
        {
          "scientific_name": "Charadrius vociferus",
          "common_name": "Chorlo tild\u00edo",
          "iconic_taxon": "Aves",
          "observations": 1,
          "taxon_id": 4793
        },
        {
          "scientific_name": "Ardea herodias",
          "common_name": "Garza morena",
          "iconic_taxon": "Aves",
          "observations": 1,
          "taxon_id": 4956
        },
        {
          "scientific_name": "Tigrisoma mexicanum",
          "common_name": "Garza tigre mexicana",
          "iconic_taxon": "Aves",
          "observations": 1,
          "taxon_id": 5049
        },
        {
          "scientific_name": "Buteo brachyurus",
          "common_name": "Aguililla cola corta",
          "iconic_taxon": "Aves",
          "observations": 1,
          "taxon_id": 5186
        },
        {
          "scientific_name": "Leptodon cayanensis",
          "common_name": "Gavil\u00e1n cabeza gris",
          "iconic_taxon": "Aves",
          "observations": 1,
          "taxon_id": 5283
        },
        {
          "scientific_name": "Geranospiza caerulescens",
          "common_name": "Gavil\u00e1n zanc\u00f3n",
          "iconic_taxon": "Aves",
          "observations": 1,
          "taxon_id": 5411
        },
        {
          "scientific_name": "Ictinia plumbea",
          "common_name": "Milano plomizo",
          "iconic_taxon": "Aves",
          "observations": 1,
          "taxon_id": 5415
        },
        {
          "scientific_name": "Amazilia yucatanensis",
          "common_name": "Colibr\u00ed Vientre Canelo",
          "iconic_taxon": "Aves",
          "observations": 1,
          "taxon_id": 5672
        },
        {
          "scientific_name": "Cyanocorax yucatanicus",
          "common_name": "Chara yucateca",
          "iconic_taxon": "Aves",
          "observations": 1,
          "taxon_id": 8470
        },
        {
          "scientific_name": "Icterus gularis",
          "common_name": "Calandria Dorso Negro Mayor",
          "iconic_taxon": "Aves",
          "observations": 1,
          "taxon_id": 9339
        }
      ],
      "bounding_box": {
        "minLon": -90.17560239939284,
        "maxLon": -89.58272924196767,
        "minLat": 18.897652467591474,
        "maxLat": 19.20471504738365
      },
      "quality_filter": "research-grade only",
      "interpretation": {
        "observations": "Total research-grade observations in area",
        "species": "Unique species identified by community",
        "note": "Citizen science data - effort varies by accessibility"
      },
      "extracted_at": "2026-01-03T11:43:11.810225"
    }
  }
}