{
  "metadata": {
    "name": "Isla San Pedro Mártir",
    "designation": "Sitio Ramsar, Humedal de Importancia Internacional",
    "designation_type": "International",
    "iucn_category": "Not Reported",
    "status": "Designated",
    "status_year": 2004,
    "governance": "Not Reported",
    "management_authority": "Not Reported",
    "reported_area_km2": 301.65,
    "country": "MEX",
    "extracted_at": "2026-01-02T13:54:22.166701",
    "categoria_de_manejo": "Reserva de la Biosfera",
    "estados": [
      "Sonora"
    ],
    "region": "Noroeste y Alto Golfo de California",
    "designaciones_internacionales": "Ramsar; UNESCO Patrimonio Mundial Natural (Serial)",
    "num_anp": "153",
    "id_anp_conanp": "ANP00201153",
    "master_list_updated_at": "2026-01-04T21:57:44.060752",
    "superficie_total_ha": 30165.24,
    "superficie_terrestre_ha": 126.99,
    "superficie_marina_ha": 30038.25,
    "primer_decreto": "2002-06-13"
  },
  "geometry": {
    "centroid": [
      -112.3090349576926,
      28.383561585172657
    ],
    "bounds": [
      [
        -112.39237780047898,
        28.30023777969799
      ],
      [
        -112.22569212618876,
        28.30023777969799
      ],
      [
        -112.22569212618876,
        28.466911110664977
      ],
      [
        -112.39237780047898,
        28.466911110664977
      ],
      [
        -112.39237780047898,
        28.30023777969799
      ]
    ]
  },
  "datasets": {
    "population": {
      "year_2020": {
        "population": 0
      }
    },
    "elevation": {
      "elevation_max": 293,
      "elevation_mean": 1.3004460127412694,
      "elevation_min": -17
    },
    "land_cover": {
      "classes": {
        "Tree cover": {
          "class_id": 10,
          "area_km2": 0.33
        },
        "Shrubland": {
          "class_id": 20,
          "area_km2": 0.32
        },
        "Grassland": {
          "class_id": 30,
          "area_km2": 0.05
        },
        "Cropland": {
          "class_id": 40,
          "area_km2": 0.01
        },
        "Built-up": {
          "class_id": 50,
          "area_km2": 0.0
        },
        "Bare/sparse vegetation": {
          "class_id": 60,
          "area_km2": 2.04
        },
        "Permanent water bodies": {
          "class_id": 80,
          "area_km2": 298.99
        },
        "Herbaceous wetland": {
          "class_id": 90,
          "area_km2": 0.01
        }
      }
    },
    "forest": {
      "tree_cover_2000_percent": 0,
      "total_loss_km2": 0.0,
      "loss_by_year": {}
    },
    "climate": {
      "annual_precipitation_mm": 66,
      "mean_max_temp_c": 29.21666666666667,
      "mean_min_temp_c": 13.858333333333334
    },
    "vegetation": {
      "NDVI_max": 0.2707,
      "NDVI_mean": 0.19118865627136022,
      "NDVI_min": 0.15662
    },
    "night_lights": {
      "avg_rad_max": 0.2666666805744171,
      "avg_rad_mean": 0.22417641720721315
    },
    "fire": {
      "burned_area_km2_by_year": {
        "2019": 0.0,
        "2020": 0.0,
        "2021": 0.0,
        "2022": 0.0,
        "2023": 0.0
      }
    },
    "biodiversity": {
      "ecoregions": [],
      "biomes": []
    },
    "human_modification": {
      "gHM_max": 0,
      "gHM_mean": 0
    },
    "water_stress": {
      "source": "WRI Aqueduct Water Risk Atlas V4",
      "resolution": "Sub-basin (HydroBASINS level 6)",
      "data_available": true,
      "sub_basins_count": 3,
      "baseline_water_stress": 1.0,
      "baseline_water_stress_category": "Extremely High (>80%)",
      "drought_risk": 0.5189,
      "drought_risk_category": "Medium",
      "interpretation": {
        "BWS": "Ratio of total water withdrawals to available supply. Protected areas often show 'No Data' due to minimal human water use.",
        "DRR": "Probability-weighted drought severity (0-1 scale)."
      },
      "note": null,
      "extracted_at": "2026-01-03T10:32:01.925714"
    },
    "gedi_biomass": {
      "source": "NASA GEDI L4A (Aboveground Biomass Density)",
      "resolution": "25m footprints",
      "data_available": true,
      "gedi_images_used": 60,
      "agbd_mean_mg_ha": 26.44,
      "agbd_max_mg_ha": 2753.55,
      "agbd_std_mg_ha": 136.34,
      "sampled_pixels": 1085,
      "anp_area_ha": 30221.0,
      "total_carbon_estimate_mt": 799.0,
      "interpretation": {
        "agbd": "Aboveground Biomass Density in Megagrams (tonnes) per hectare",
        "total_carbon": "Rough estimate of total aboveground carbon stock in megatonnes"
      },
      "extracted_at": "2026-01-03T11:06:52.187220"
    },
    "mangroves": {
      "source": "ESA WorldCover 2021",
      "data_available": false,
      "mangrove_extent_km2": 0,
      "note": "No mangrove pixels detected (class 95) within ANP boundary",
      "extracted_at": "2026-01-03T11:36:33.190834"
    }
  },
  "external_data": {
    "gbif_species": {
      "source": "GBIF (Global Biodiversity Information Facility)",
      "query_date": "2026-01-03T00:16:30.372112",
      "total_occurrences": 3370,
      "unique_species": 112,
      "bounding_box": {
        "minLon": -112.39237780047898,
        "maxLon": -112.22569212618876,
        "minLat": 28.300237779698016,
        "maxLat": 28.466910003056118
      },
      "species_by_class": {
        "Mammalia": 4,
        "Magnoliopsida": 1,
        "Aves": 28,
        "Malacostraca": 4,
        "Scyphozoa": 1,
        "Dinophyceae": 1,
        "Gastropoda": 9,
        "Asteroidea": 8,
        "Holothuroidea": 1,
        "Unknown": 42,
        "Anthozoa": 1,
        "Demospongiae": 1,
        "Echinoidea": 4,
        "Testudines": 1,
        "Elasmobranchii": 4,
        "Ophiuroidea": 1,
        "Hydrozoa": 1
      },
      "top_species": [
        {
          "scientific_name": "Sula nebouxii",
          "kingdom": "Animalia",
          "phylum": "Chordata",
          "class": "Aves",
          "order": "Suliformes",
          "family": "Sulidae",
          "genus": "Sula",
          "taxon_key": 2480978,
          "occurrences": 108
        },
        {
          "scientific_name": "Phaethon aethereus",
          "kingdom": "Animalia",
          "phylum": "Chordata",
          "class": "Aves",
          "order": "Phaethontiformes",
          "family": "Phaethontidae",
          "genus": "Phaethon",
          "taxon_key": 9743996,
          "occurrences": 96
        },
        {
          "scientific_name": "Pelecanus occidentalis",
          "kingdom": "Animalia",
          "phylum": "Chordata",
          "class": "Aves",
          "order": "Pelecaniformes",
          "family": "Pelecanidae",
          "genus": "Pelecanus",
          "taxon_key": 5229158,
          "occurrences": 67
        },
        {
          "scientific_name": "Zalophus californianus",
          "kingdom": "Animalia",
          "phylum": "Chordata",
          "class": "Mammalia",
          "order": "Carnivora",
          "family": "Otariidae",
          "genus": "Zalophus",
          "taxon_key": 2433458,
          "occurrences": 58
        },
        {
          "scientific_name": "Larus livens",
          "kingdom": "Animalia",
          "phylum": "Chordata",
          "class": "Aves",
          "order": "Charadriiformes",
          "family": "Laridae",
          "genus": "Larus",
          "taxon_key": 2481154,
          "occurrences": 54
        },
        {
          "scientific_name": "Larus heermanni",
          "kingdom": "Animalia",
          "phylum": "Chordata",
          "class": "Aves",
          "order": "Charadriiformes",
          "family": "Laridae",
          "genus": "Larus",
          "taxon_key": 2481130,
          "occurrences": 39
        },
        {
          "scientific_name": "Urile penicillatus",
          "kingdom": "Animalia",
          "phylum": "Chordata",
          "class": "Aves",
          "order": "Suliformes",
          "family": "Phalacrocoracidae",
          "genus": "Urile",
          "taxon_key": 10682451,
          "occurrences": 38
        },
        {
          "scientific_name": "Fregata magnificens",
          "kingdom": "Animalia",
          "phylum": "Chordata",
          "class": "Aves",
          "order": "Suliformes",
          "family": "Fregatidae",
          "genus": "Fregata",
          "taxon_key": 2480189,
          "occurrences": 35
        },
        {
          "scientific_name": "Pachycereus pringlei",
          "kingdom": "Plantae",
          "phylum": "Tracheophyta",
          "class": "Magnoliopsida",
          "order": "Caryophyllales",
          "family": "Cactaceae",
          "genus": "Pachycereus",
          "taxon_key": 7282285,
          "occurrences": 31
        },
        {
          "scientific_name": "Corvus corax",
          "kingdom": "Animalia",
          "phylum": "Chordata",
          "class": "Aves",
          "order": "Passeriformes",
          "family": "Corvidae",
          "genus": "Corvus",
          "taxon_key": 2482492,
          "occurrences": 27
        },
        {
          "scientific_name": "Podiceps nigricollis",
          "kingdom": "Animalia",
          "phylum": "Chordata",
          "class": "Aves",
          "order": "Podicipediformes",
          "family": "Podicipedidae",
          "genus": "Podiceps",
          "taxon_key": 2482065,
          "occurrences": 22
        },
        {
          "scientific_name": "Hydrobates melania",
          "kingdom": "Animalia",
          "phylum": "Chordata",
          "class": "Aves",
          "order": "Procellariiformes",
          "family": "Hydrobatidae",
          "genus": "Hydrobates",
          "taxon_key": 11068810,
          "occurrences": 20
        },
        {
          "scientific_name": "Tambja abdere",
          "kingdom": "Animalia",
          "phylum": "Mollusca",
          "class": "Gastropoda",
          "order": "Nudibranchia",
          "family": "Polyceridae",
          "genus": "Tambja",
          "taxon_key": 5859537,
          "occurrences": 18
        },
        {
          "scientific_name": "Oceanodroma microsoma",
          "kingdom": "Animalia",
          "phylum": "Chordata",
          "class": "Aves",
          "order": "Procellariiformes",
          "family": "Hydrobatidae",
          "genus": "Oceanodroma",
          "taxon_key": 2481999,
          "occurrences": 17
        },
        {
          "scientific_name": "Synthliboramphus craveri",
          "kingdom": "Animalia",
          "phylum": "Chordata",
          "class": "Aves",
          "order": "Charadriiformes",
          "family": "Alcidae",
          "genus": "Synthliboramphus",
          "taxon_key": 2481348,
          "occurrences": 16
        },
        {
          "scientific_name": "Falco peregrinus",
          "kingdom": "Animalia",
          "phylum": "Chordata",
          "class": "Aves",
          "order": "Falconiformes",
          "family": "Falconidae",
          "genus": "Falco",
          "taxon_key": 2481047,
          "occurrences": 15
        },
        {
          "scientific_name": "Thalasseus elegans",
          "kingdom": "Animalia",
          "phylum": "Chordata",
          "class": "Aves",
          "order": "Charadriiformes",
          "family": "Laridae",
          "genus": "Thalasseus",
          "taxon_key": 2481285,
          "occurrences": 14
        },
        {
          "scientific_name": "Mycteroperca rosacea",
          "kingdom": "Animalia",
          "phylum": "Chordata",
          "class": null,
          "order": "Perciformes",
          "family": "Serranidae",
          "genus": "Mycteroperca",
          "taxon_key": 2389010,
          "occurrences": 11
        },
        {
          "scientific_name": "Paranthias colonus",
          "kingdom": "Animalia",
          "phylum": "Chordata",
          "class": null,
          "order": "Perciformes",
          "family": "Serranidae",
          "genus": "Paranthias",
          "taxon_key": 2387693,
          "occurrences": 11
        },
        {
          "scientific_name": "Phalacrocorax auritus",
          "kingdom": "Animalia",
          "phylum": "Chordata",
          "class": "Aves",
          "order": "Suliformes",
          "family": "Phalacrocoracidae",
          "genus": "Phalacrocorax",
          "taxon_key": 2481875,
          "occurrences": 11
        },
        {
          "scientific_name": "Malacoctenus hubbsi",
          "kingdom": "Animalia",
          "phylum": "Chordata",
          "class": null,
          "order": "Perciformes",
          "family": "Labrisomidae",
          "genus": "Malacoctenus",
          "taxon_key": 2389511,
          "occurrences": 10
        },
        {
          "scientific_name": "Lythrypnus dalli",
          "kingdom": "Animalia",
          "phylum": "Chordata",
          "class": null,
          "order": "Perciformes",
          "family": "Gobiidae",
          "genus": "Lythrypnus",
          "taxon_key": 2376016,
          "occurrences": 9
        },
        {
          "scientific_name": "Panulirus inflatus",
          "kingdom": "Animalia",
          "phylum": "Arthropoda",
          "class": "Malacostraca",
          "order": "Decapoda",
          "family": "Palinuridae",
          "genus": "Panulirus",
          "taxon_key": 2221642,
          "occurrences": 9
        },
        {
          "scientific_name": "Ardea herodias",
          "kingdom": "Animalia",
          "phylum": "Chordata",
          "class": "Aves",
          "order": "Pelecaniformes",
          "family": "Ardeidae",
          "genus": "Ardea",
          "taxon_key": 9630752,
          "occurrences": 9
        },
        {
          "scientific_name": "Actitis macularius",
          "kingdom": "Animalia",
          "phylum": "Chordata",
          "class": "Aves",
          "order": "Charadriiformes",
          "family": "Scolopacidae",
          "genus": "Actitis",
          "taxon_key": 2481798,
          "occurrences": 9
        },
        {
          "scientific_name": "Scorpaenodes xyris",
          "kingdom": "Animalia",
          "phylum": "Chordata",
          "class": null,
          "order": "Scorpaeniformes",
          "family": "Scorpaenidae",
          "genus": "Scorpaenodes",
          "taxon_key": 2334410,
          "occurrences": 9
        },
        {
          "scientific_name": "Pharia pyramidata",
          "kingdom": "Animalia",
          "phylum": "Echinodermata",
          "class": "Asteroidea",
          "order": "Valvatida",
          "family": "Ophidiasteridae",
          "genus": "Pharia",
          "taxon_key": 5842614,
          "occurrences": 8
        },
        {
          "scientific_name": "Phataria unifascialis",
          "kingdom": "Animalia",
          "phylum": "Echinodermata",
          "class": "Asteroidea",
          "order": "Valvatida",
          "family": "Ophidiasteridae",
          "genus": "Phataria",
          "taxon_key": 2272422,
          "occurrences": 8
        },
        {
          "scientific_name": "Thalasseus maximus",
          "kingdom": "Animalia",
          "phylum": "Chordata",
          "class": "Aves",
          "order": "Charadriiformes",
          "family": "Laridae",
          "genus": "Thalasseus",
          "taxon_key": 5789281,
          "occurrences": 8
        },
        {
          "scientific_name": "Grapsus grapsus",
          "kingdom": "Animalia",
          "phylum": "Arthropoda",
          "class": "Malacostraca",
          "order": "Decapoda",
          "family": "Grapsidae",
          "genus": "Grapsus",
          "taxon_key": 2225819,
          "occurrences": 7
        },
        {
          "scientific_name": "Pentaceraster cumingi",
          "kingdom": "Animalia",
          "phylum": "Echinodermata",
          "class": "Asteroidea",
          "order": "Valvatida",
          "family": "Oreasteridae",
          "genus": "Pentaceraster",
          "taxon_key": 2272865,
          "occurrences": 7
        },
        {
          "scientific_name": "Mithrodia bradleyi",
          "kingdom": "Animalia",
          "phylum": "Echinodermata",
          "class": "Asteroidea",
          "order": "Valvatida",
          "family": "Mithrodiidae",
          "genus": "Mithrodia",
          "taxon_key": 2272773,
          "occurrences": 7
        },
        {
          "scientific_name": "Chromis limbaughi",
          "kingdom": "Animalia",
          "phylum": "Chordata",
          "class": null,
          "order": "Perciformes",
          "family": "Pomacentridae",
          "genus": "Chromis",
          "taxon_key": 5212155,
          "occurrences": 7
        },
        {
          "scientific_name": "Bodianus diplotaenia",
          "kingdom": "Animalia",
          "phylum": "Chordata",
          "class": null,
          "order": "Perciformes",
          "family": "Labridae",
          "genus": "Bodianus",
          "taxon_key": 5209721,
          "occurrences": 7
        },
        {
          "scientific_name": "Holacanthus passer",
          "kingdom": "Animalia",
          "phylum": "Chordata",
          "class": null,
          "order": "Perciformes",
          "family": "Pomacanthidae",
          "genus": "Holacanthus",
          "taxon_key": 5211449,
          "occurrences": 7
        },
        {
          "scientific_name": "Thalassoma lucasanum",
          "kingdom": "Animalia",
          "phylum": "Chordata",
          "class": null,
          "order": "Perciformes",
          "family": "Labridae",
          "genus": "Thalassoma",
          "taxon_key": 2384480,
          "occurrences": 7
        },
        {
          "scientific_name": "Tursiops truncatus",
          "kingdom": "Animalia",
          "phylum": "Chordata",
          "class": "Mammalia",
          "order": "Cetacea",
          "family": "Delphinidae",
          "genus": "Tursiops",
          "taxon_key": 2440447,
          "occurrences": 6
        },
        {
          "scientific_name": "Elysia diomedea",
          "kingdom": "Animalia",
          "phylum": "Mollusca",
          "class": "Gastropoda",
          "order": null,
          "family": "Plakobranchidae",
          "genus": "Elysia",
          "taxon_key": 5859300,
          "occurrences": 6
        },
        {
          "scientific_name": "Muraena lentiginosa",
          "kingdom": "Animalia",
          "phylum": "Chordata",
          "class": null,
          "order": "Anguilliformes",
          "family": "Muraenidae",
          "genus": "Muraena",
          "taxon_key": 2404308,
          "occurrences": 6
        },
        {
          "scientific_name": "Gymnothorax castaneus",
          "kingdom": "Animalia",
          "phylum": "Chordata",
          "class": null,
          "order": "Anguilliformes",
          "family": "Muraenidae",
          "genus": "Gymnothorax",
          "taxon_key": 2404111,
          "occurrences": 6
        },
        {
          "scientific_name": "Acanthaster planci",
          "kingdom": "Animalia",
          "phylum": "Echinodermata",
          "class": "Asteroidea",
          "order": "Valvatida",
          "family": "Acanthasteridae",
          "genus": "Acanthaster",
          "taxon_key": 2271208,
          "occurrences": 6
        },
        {
          "scientific_name": "Apogon retrosella",
          "kingdom": "Animalia",
          "phylum": "Chordata",
          "class": null,
          "order": "Perciformes",
          "family": "Apogonidae",
          "genus": "Apogon",
          "taxon_key": 5211603,
          "occurrences": 6
        },
        {
          "scientific_name": "Epinephelus labriformis",
          "kingdom": "Animalia",
          "phylum": "Chordata",
          "class": null,
          "order": "Perciformes",
          "family": "Serranidae",
          "genus": "Epinephelus",
          "taxon_key": 2388503,
          "occurrences": 6
        },
        {
          "scientific_name": "Tyrannodoris tigris",
          "kingdom": "Animalia",
          "phylum": "Mollusca",
          "class": "Gastropoda",
          "order": "Nudibranchia",
          "family": "Polyceridae",
          "genus": "Tyrannodoris",
          "taxon_key": 9282571,
          "occurrences": 5
        },
        {
          "scientific_name": "Isostichopus fuscus",
          "kingdom": "Animalia",
          "phylum": "Echinodermata",
          "class": "Holothuroidea",
          "order": "Synallactida",
          "family": "Stichopodidae",
          "genus": "Isostichopus",
          "taxon_key": 5842682,
          "occurrences": 5
        },
        {
          "scientific_name": "Alphestes immaculatus",
          "kingdom": "Animalia",
          "phylum": "Chordata",
          "class": null,
          "order": "Perciformes",
          "family": "Serranidae",
          "genus": "Alphestes",
          "taxon_key": 2387800,
          "occurrences": 5
        },
        {
          "scientific_name": "Chelonia mydas",
          "kingdom": "Animalia",
          "phylum": "Chordata",
          "class": "Testudines",
          "order": null,
          "family": "Cheloniidae",
          "genus": "Chelonia",
          "taxon_key": 2442225,
          "occurrences": 5
        },
        {
          "scientific_name": "Gavia pacifica",
          "kingdom": "Animalia",
          "phylum": "Chordata",
          "class": "Aves",
          "order": "Gaviiformes",
          "family": "Gaviidae",
          "genus": "Gavia",
          "taxon_key": 2481955,
          "occurrences": 5
        },
        {
          "scientific_name": "Larus delawarensis",
          "kingdom": "Animalia",
          "phylum": "Chordata",
          "class": "Aves",
          "order": "Charadriiformes",
          "family": "Laridae",
          "genus": "Larus",
          "taxon_key": 2481134,
          "occurrences": 5
        },
        {
          "scientific_name": "Leucophaeus atricilla",
          "kingdom": "Animalia",
          "phylum": "Chordata",
          "class": "Aves",
          "order": "Charadriiformes",
          "family": "Laridae",
          "genus": "Leucophaeus",
          "taxon_key": 6065844,
          "occurrences": 5
        }
      ]
    },
    "iucn_threatened": {
      "source": "GBIF IUCN Red List data",
      "critically_endangered": [
        "Stereolepis gigas"
      ],
      "endangered": [
        "Isostichopus fuscus",
        "Chelonia mydas",
        "Balaenoptera musculus"
      ],
      "vulnerable": [
        "Synthliboramphus craveri",
        "Uta palmeri",
        "Aspidoscelis martyris",
        "Physeter macrocephalus"
      ],
      "total_threatened": 8
    },
    "simec_nom059": {
      "source": "CONANP SIMEC (NOM-059-SEMARNAT-2010)",
      "matched_simec_name": "RB Isla San Pedro Mártir",
      "endangered_P": [
        "Caretta caretta",
        "Chelonia mydas",
        "Eretmochelys imbricata",
        "Myotis vivesi",
        "Puffinus opisthomelas",
        "Synthliboramphus craveri"
      ],
      "threatened_A": [
        "Carcharodon carcharias",
        "Lampropeltis getula",
        "Oceanodroma Melania",
        "Oceanodroma microsoma",
        "Pelecanus occidentalis californicus",
        "Phaethon aethereus",
        "Uta palmeri"
      ],
      "special_protection_Pr": [
        "Ardea herodias santilucae",
        "Aspidoscelis martyris",
        "Balaenoptera acutorostrata",
        "Balaenoptera edeni",
        "Balaenoptera musculus",
        "Balaenoptera physalus",
        "Berardius bairdii",
        "Chromis limbaughi",
        "Crotalus atrox",
        "Delphinus capensis",
        "Eschrichtius robustus",
        "Falco peregrinus",
        "Globicephala macrorhynchus",
        "Holacanthus passer",
        "Kogia sima",
        "Larus heermanni",
        "Larus livens",
        "Opistognathus rosenblatti",
        "Orcinus orca",
        "Physeter macrocephalus",
        "Pinctada mazatlanica",
        "Pomacanthus zonipectus",
        "Spondylus calcifer",
        "Sterna elegans",
        "Sula nebouxii",
        "Tursiops truncates",
        "Zalophus californianus",
        "Ziphius cavirostris"
      ],
      "probably_extinct_E": [],
      "total_species": 41
    },
    "nom059_enciclovida": {
      "source": "NOM-059-SEMARNAT (via Enciclovida)",
      "endangered_P": [],
      "threatened_A": [],
      "special_protection_Pr": [],
      "probably_extinct_E": [],
      "total_nom059": 0,
      "species_checked": 50
    },
    "inegi_census": {
      "error": "No ITER data files found or no localities in bbox"
    },
    "extracted_at": "2026-01-03T00:17:33.957070",
    "coneval_irs": {
      "source": "CONEVAL IRS 2020",
      "data_available": false,
      "reason": "No municipalities found within ANP bounds",
      "note": "This may be expected for marine ANPs or remote islands"
    },
    "inaturalist": {
      "source": "iNaturalist (Naturalista)",
      "data_available": true,
      "total_observations": 822,
      "unique_species": 175,
      "species_by_group": {
        "Plantae": 20,
        "Mammalia": 6,
        "Aves": 23,
        "Mollusca": 21,
        "Actinopterygii": 60,
        "Animalia": 37,
        "Reptilia": 4,
        "Insecta": 3,
        "Chromista": 1
      },
      "top_species": [
        {
          "scientific_name": "Pachycereus pringlei",
          "common_name": "Cardón",
          "iconic_taxon": "Plantae",
          "observations": 77,
          "taxon_id": 199206
        },
        {
          "scientific_name": "Zalophus californianus",
          "common_name": "Lobo marino californiano",
          "iconic_taxon": "Mammalia",
          "observations": 71,
          "taxon_id": 41740
        },
        {
          "scientific_name": "Sula nebouxii",
          "common_name": "Bobo Patas Azules",
          "iconic_taxon": "Aves",
          "observations": 55,
          "taxon_id": 3786
        },
        {
          "scientific_name": "Sula brewsteri",
          "common_name": "Piquero de Cocos",
          "iconic_taxon": "Aves",
          "observations": 47,
          "taxon_id": 1578501
        },
        {
          "scientific_name": "Pelecanus occidentalis",
          "common_name": "Pelícano café",
          "iconic_taxon": "Aves",
          "observations": 24,
          "taxon_id": 4328
        },
        {
          "scientific_name": "Phaethon aethereus",
          "common_name": "Rabijunco pico rojo",
          "iconic_taxon": "Aves",
          "observations": 19,
          "taxon_id": 4317
        },
        {
          "scientific_name": "Tursiops truncatus",
          "common_name": "Delfín mular",
          "iconic_taxon": "Mammalia",
          "observations": 19,
          "taxon_id": 41482
        },
        {
          "scientific_name": "Tambja abdere",
          "common_name": "babosa viscosa",
          "iconic_taxon": "Mollusca",
          "observations": 17,
          "taxon_id": 50093
        },
        {
          "scientific_name": "Delphinus delphis",
          "common_name": "Delfín común",
          "iconic_taxon": "Mammalia",
          "observations": 15,
          "taxon_id": 41526
        },
        {
          "scientific_name": "Larus livens",
          "common_name": "Gaviota Bajacaliforniana",
          "iconic_taxon": "Aves",
          "observations": 13,
          "taxon_id": 4354
        },
        {
          "scientific_name": "Holacanthus passer",
          "common_name": "Ángel real",
          "iconic_taxon": "Actinopterygii",
          "observations": 12,
          "taxon_id": 56797
        },
        {
          "scientific_name": "Bodianus diplotaenia",
          "common_name": "vieja mexicana",
          "iconic_taxon": "Actinopterygii",
          "observations": 12,
          "taxon_id": 57333
        },
        {
          "scientific_name": "Gymnothorax castaneus",
          "common_name": "Morena verde panámica",
          "iconic_taxon": "Actinopterygii",
          "observations": 11,
          "taxon_id": 85113
        },
        {
          "scientific_name": "Mycteroperca rosacea",
          "common_name": "Cabrilla sardinera",
          "iconic_taxon": "Actinopterygii",
          "observations": 11,
          "taxon_id": 106312
        },
        {
          "scientific_name": "Phataria unifascialis",
          "common_name": "Estrella azul del Pacífico",
          "iconic_taxon": "Animalia",
          "observations": 11,
          "taxon_id": 195833
        },
        {
          "scientific_name": "Thalassoma lucasanum",
          "common_name": "Arcoiris de Cortés",
          "iconic_taxon": "Actinopterygii",
          "observations": 10,
          "taxon_id": 49493
        },
        {
          "scientific_name": "Pentaceraster cumingi",
          "common_name": "Estrella cojín",
          "iconic_taxon": "Animalia",
          "observations": 9,
          "taxon_id": 56775
        },
        {
          "scientific_name": "Scorpaena mystes",
          "common_name": "Escorpión roquero",
          "iconic_taxon": "Actinopterygii",
          "observations": 9,
          "taxon_id": 112345
        },
        {
          "scientific_name": "Pharia pyramidata",
          "common_name": "Estrella amarilla",
          "iconic_taxon": "Animalia",
          "observations": 9,
          "taxon_id": 344899
        },
        {
          "scientific_name": "Grapsus grapsus",
          "common_name": "Zapaya",
          "iconic_taxon": "Animalia",
          "observations": 8,
          "taxon_id": 55295
        },
        {
          "scientific_name": "Panulirus inflatus",
          "common_name": "Langosta azul",
          "iconic_taxon": "Animalia",
          "observations": 8,
          "taxon_id": 108360
        },
        {
          "scientific_name": "Urile penicillatus",
          "common_name": "Cormorán de Brandt",
          "iconic_taxon": "Aves",
          "observations": 8,
          "taxon_id": 1289607
        },
        {
          "scientific_name": "Diodon holocanthus",
          "common_name": "Pez erizo apache",
          "iconic_taxon": "Actinopterygii",
          "observations": 7,
          "taxon_id": 49269
        },
        {
          "scientific_name": "Cirrhitus rivulatus",
          "common_name": "Mero chino",
          "iconic_taxon": "Actinopterygii",
          "observations": 7,
          "taxon_id": 97880
        },
        {
          "scientific_name": "Malacoctenus hubbsi",
          "common_name": "trambollo rojo",
          "iconic_taxon": "Actinopterygii",
          "observations": 7,
          "taxon_id": 105113
        },
        {
          "scientific_name": "Felimare californiensis",
          "common_name": "Nudibranquio de Ghiselin",
          "iconic_taxon": "Mollusca",
          "observations": 7,
          "taxon_id": 469723
        },
        {
          "scientific_name": "Crotalus atrox",
          "common_name": "Cascabel de diamantes",
          "iconic_taxon": "Reptilia",
          "observations": 6,
          "taxon_id": 30764
        },
        {
          "scientific_name": "Uta palmeri",
          "common_name": "Lagartija manchada de la isla de  San Pedro",
          "iconic_taxon": "Reptilia",
          "observations": 6,
          "taxon_id": 36101
        },
        {
          "scientific_name": "Chelonia mydas",
          "common_name": "Tortuga verde",
          "iconic_taxon": "Reptilia",
          "observations": 6,
          "taxon_id": 39659
        },
        {
          "scientific_name": "Epinephelus labriformis",
          "common_name": "Cabrilla piedrera",
          "iconic_taxon": "Actinopterygii",
          "observations": 6,
          "taxon_id": 67529
        }
      ],
      "bounding_box": {
        "minLon": -112.39237780047898,
        "maxLon": -112.22569212618876,
        "minLat": 28.30023777969799,
        "maxLat": 28.466911110664977
      },
      "quality_filter": "research-grade only",
      "interpretation": {
        "observations": "Total research-grade observations in area",
        "species": "Unique species identified by community",
        "note": "Citizen science data - effort varies by accessibility"
      },
      "extracted_at": "2026-01-03T11:48:11.902736"
    }
  }
}