{
  "metadata": {
    "name": "Playa de Mismaloya",
    "designation": "Santuario",
    "designation_type": "National",
    "iucn_category": "II",
    "status": "Designated",
    "status_year": 2002,
    "governance": "Federal or national ministry or agency",
    "management_authority": "National Commission of Natural Protected Areas",
    "reported_area_km2": 6.28446882,
    "country": "MEX",
    "extracted_at": "2026-01-02T13:51:48.978700"
  },
  "geometry": {
    "centroid": [
      -105.42513800859072,
      19.929611429380216
    ],
    "bounds": [
      [
        -105.58197488876448,
        19.669576298531243
      ],
      [
        -105.24700282995568,
        19.669576298531243
      ],
      [
        -105.24700282995568,
        20.239266596551072
      ],
      [
        -105.58197488876448,
        20.239266596551072
      ],
      [
        -105.58197488876448,
        19.669576298531243
      ]
    ]
  },
  "datasets": {
    "population": {
      "year_2020": {
        "population": 120.6546964615051
      }
    },
    "elevation": {
      "elevation_max": 41,
      "elevation_mean": 4.499835293610817,
      "elevation_min": -5
    },
    "land_cover": {
      "classes": {
        "Tree cover": {
          "class_id": 10,
          "area_km2": 0.21
        },
        "Shrubland": {
          "class_id": 20,
          "area_km2": 0.02
        },
        "Grassland": {
          "class_id": 30,
          "area_km2": 0.98
        },
        "Cropland": {
          "class_id": 40,
          "area_km2": 0.0
        },
        "Built-up": {
          "class_id": 50,
          "area_km2": 0.01
        },
        "Bare/sparse vegetation": {
          "class_id": 60,
          "area_km2": 3.95
        },
        "Permanent water bodies": {
          "class_id": 80,
          "area_km2": 1.04
        },
        "Mangroves": {
          "class_id": 95,
          "area_km2": 0.07
        }
      }
    },
    "forest": {
      "tree_cover_2000_percent": 0.025752619760872265,
      "total_loss_km2": 0.0,
      "loss_by_year": {}
    },
    "climate": {
      "annual_precipitation_mm": 727.3146067415731,
      "mean_max_temp_c": 32.158052434456934,
      "mean_min_temp_c": 19.156367041198504
    },
    "vegetation": {
      "NDVI_max": 0.8114565217391304,
      "NDVI_mean": 0.5736249063434945,
      "NDVI_min": 0.254875
    },
    "night_lights": {
      "avg_rad_max": 1.055833339691162,
      "avg_rad_mean": 0.25364347636839857
    },
    "fire": {
      "burned_area_km2_by_year": {
        "2019": 0.0,
        "2020": 0.0,
        "2021": 0.0,
        "2022": 0.0,
        "2023": 0.0
      }
    },
    "biodiversity": {
      "ecoregions": [
        "Jalisco dry forests",
        "Northern Mesoamerican Pacific mangroves"
      ],
      "biomes": [
        "Tropical & Subtropical Dry Broadleaf Forests",
        "Mangroves"
      ]
    },
    "human_modification": {
      "gHM_max": 0.5785695314407349,
      "gHM_mean": 0.26648980540987227
    },
    "water_stress": {
      "source": "WRI Aqueduct Water Risk Atlas V4",
      "resolution": "Sub-basin (HydroBASINS level 6)",
      "data_available": true,
      "sub_basins_count": 6,
      "baseline_water_stress": 0.4653,
      "baseline_water_stress_category": "High (40-80%)",
      "drought_risk": 0.515,
      "drought_risk_category": "Medium",
      "interpretation": {
        "BWS": "Ratio of total water withdrawals to available supply. Protected areas often show 'No Data' due to minimal human water use.",
        "DRR": "Probability-weighted drought severity (0-1 scale)."
      },
      "note": null,
      "extracted_at": "2026-01-03T10:33:14.279360"
    },
    "gedi_biomass": {
      "source": "NASA GEDI L4A (Aboveground Biomass Density)",
      "resolution": "25m footprints",
      "data_available": true,
      "gedi_images_used": 60,
      "agbd_mean_mg_ha": 54.14,
      "agbd_max_mg_ha": 1910.79,
      "agbd_std_mg_ha": 70.85,
      "sampled_pixels": 223072,
      "anp_area_ha": 221783.0,
      "total_carbon_estimate_mt": 12007.0,
      "interpretation": {
        "agbd": "Aboveground Biomass Density in Megagrams (tonnes) per hectare",
        "total_carbon": "Rough estimate of total aboveground carbon stock in megatonnes"
      },
      "extracted_at": "2026-01-03T11:14:21.947336"
    }
  },
  "external_data": {
    "gbif_species": {
      "source": "GBIF (Global Biodiversity Information Facility)",
      "query_date": "2026-01-03T01:31:45.296901",
      "total_occurrences": 17687,
      "unique_species": 142,
      "bounding_box": {
        "minLon": -105.58197488876448,
        "maxLon": -105.24700282995568,
        "minLat": 19.66957629853127,
        "maxLat": 20.239266596551047
      },
      "species_by_class": {
        "Gastropoda": 1,
        "Malacostraca": 2,
        "Aves": 108,
        "Arachnida": 3,
        "Magnoliopsida": 2,
        "Liliopsida": 1,
        "Insecta": 6,
        "Amphibia": 4,
        "Squamata": 13,
        "Testudines": 2
      },
      "top_species": [
        {
          "scientific_name": "Cathartes aura",
          "kingdom": "Animalia",
          "phylum": "Chordata",
          "class": "Aves",
          "order": "Accipitriformes",
          "family": "Cathartidae",
          "genus": "Cathartes",
          "taxon_key": 2481930,
          "occurrences": 257
        },
        {
          "scientific_name": "Tyrannus melancholicus",
          "kingdom": "Animalia",
          "phylum": "Chordata",
          "class": "Aves",
          "order": "Passeriformes",
          "family": "Tyrannidae",
          "genus": "Tyrannus",
          "taxon_key": 5229662,
          "occurrences": 242
        },
        {
          "scientific_name": "Coragyps atratus",
          "kingdom": "Animalia",
          "phylum": "Chordata",
          "class": "Aves",
          "order": "Accipitriformes",
          "family": "Cathartidae",
          "genus": "Coragyps",
          "taxon_key": 2481942,
          "occurrences": 224
        },
        {
          "scientific_name": "Phalacrocorax brasilianus",
          "kingdom": "Animalia",
          "phylum": "Chordata",
          "class": "Aves",
          "order": "Suliformes",
          "family": "Phalacrocoracidae",
          "genus": "Phalacrocorax",
          "taxon_key": 9399113,
          "occurrences": 220
        },
        {
          "scientific_name": "Fregata magnificens",
          "kingdom": "Animalia",
          "phylum": "Chordata",
          "class": "Aves",
          "order": "Suliformes",
          "family": "Fregatidae",
          "genus": "Fregata",
          "taxon_key": 2480189,
          "occurrences": 212
        },
        {
          "scientific_name": "Egretta thula",
          "kingdom": "Animalia",
          "phylum": "Chordata",
          "class": "Aves",
          "order": "Pelecaniformes",
          "family": "Ardeidae",
          "genus": "Egretta",
          "taxon_key": 2480873,
          "occurrences": 204
        },
        {
          "scientific_name": "Pelecanus occidentalis",
          "kingdom": "Animalia",
          "phylum": "Chordata",
          "class": "Aves",
          "order": "Pelecaniformes",
          "family": "Pelecanidae",
          "genus": "Pelecanus",
          "taxon_key": 5229158,
          "occurrences": 198
        },
        {
          "scientific_name": "Ardea alba",
          "kingdom": "Animalia",
          "phylum": "Chordata",
          "class": "Aves",
          "order": "Pelecaniformes",
          "family": "Ardeidae",
          "genus": "Ardea",
          "taxon_key": 9752617,
          "occurrences": 190
        },
        {
          "scientific_name": "Caracara plancus",
          "kingdom": "Animalia",
          "phylum": "Chordata",
          "class": "Aves",
          "order": "Falconiformes",
          "family": "Falconidae",
          "genus": "Caracara",
          "taxon_key": 2480989,
          "occurrences": 188
        },
        {
          "scientific_name": "Melanerpes chrysogenys",
          "kingdom": "Animalia",
          "phylum": "Chordata",
          "class": "Aves",
          "order": "Piciformes",
          "family": "Picidae",
          "genus": "Melanerpes",
          "taxon_key": 2478102,
          "occurrences": 176
        },
        {
          "scientific_name": "Columbina inca",
          "kingdom": "Animalia",
          "phylum": "Chordata",
          "class": "Aves",
          "order": "Columbiformes",
          "family": "Columbidae",
          "genus": "Columbina",
          "taxon_key": 2495863,
          "occurrences": 174
        },
        {
          "scientific_name": "Hirundo rustica",
          "kingdom": "Animalia",
          "phylum": "Chordata",
          "class": "Aves",
          "order": "Passeriformes",
          "family": "Hirundinidae",
          "genus": "Hirundo",
          "taxon_key": 9515886,
          "occurrences": 161
        },
        {
          "scientific_name": "Quiscalus mexicanus",
          "kingdom": "Animalia",
          "phylum": "Chordata",
          "class": "Aves",
          "order": "Passeriformes",
          "family": "Icteridae",
          "genus": "Quiscalus",
          "taxon_key": 9476062,
          "occurrences": 158
        },
        {
          "scientific_name": "Crotophaga sulcirostris",
          "kingdom": "Animalia",
          "phylum": "Chordata",
          "class": "Aves",
          "order": "Cuculiformes",
          "family": "Cuculidae",
          "genus": "Crotophaga",
          "taxon_key": 2496211,
          "occurrences": 156
        },
        {
          "scientific_name": "Fulica americana",
          "kingdom": "Animalia",
          "phylum": "Chordata",
          "class": "Aves",
          "order": "Gruiformes",
          "family": "Rallidae",
          "genus": "Fulica",
          "taxon_key": 2474393,
          "occurrences": 154
        },
        {
          "scientific_name": "Pitangus sulphuratus",
          "kingdom": "Animalia",
          "phylum": "Chordata",
          "class": "Aves",
          "order": "Passeriformes",
          "family": "Tyrannidae",
          "genus": "Pitangus",
          "taxon_key": 2482755,
          "occurrences": 154
        },
        {
          "scientific_name": "Zenaida asiatica",
          "kingdom": "Animalia",
          "phylum": "Chordata",
          "class": "Aves",
          "order": "Columbiformes",
          "family": "Columbidae",
          "genus": "Zenaida",
          "taxon_key": 2495370,
          "occurrences": 148
        },
        {
          "scientific_name": "Himantopus mexicanus",
          "kingdom": "Animalia",
          "phylum": "Chordata",
          "class": "Aves",
          "order": "Charadriiformes",
          "family": "Recurvirostridae",
          "genus": "Himantopus",
          "taxon_key": 5229128,
          "occurrences": 144
        },
        {
          "scientific_name": "Spatula discors",
          "kingdom": "Animalia",
          "phylum": "Chordata",
          "class": "Aves",
          "order": "Anseriformes",
          "family": "Anatidae",
          "genus": "Spatula",
          "taxon_key": 9422220,
          "occurrences": 143
        },
        {
          "scientific_name": "Peucaea ruficauda",
          "kingdom": "Animalia",
          "phylum": "Chordata",
          "class": "Aves",
          "order": "Passeriformes",
          "family": "Passerellidae",
          "genus": "Peucaea",
          "taxon_key": 7341569,
          "occurrences": 137
        },
        {
          "scientific_name": "Passerina leclancherii",
          "kingdom": "Animalia",
          "phylum": "Chordata",
          "class": "Aves",
          "order": "Passeriformes",
          "family": "Cardinalidae",
          "genus": "Passerina",
          "taxon_key": 5230870,
          "occurrences": 134
        },
        {
          "scientific_name": "Eudocimus albus",
          "kingdom": "Animalia",
          "phylum": "Chordata",
          "class": "Aves",
          "order": "Pelecaniformes",
          "family": "Threskiornithidae",
          "genus": "Eudocimus",
          "taxon_key": 5229205,
          "occurrences": 132
        },
        {
          "scientific_name": "Polioptila caerulea",
          "kingdom": "Animalia",
          "phylum": "Chordata",
          "class": "Aves",
          "order": "Passeriformes",
          "family": "Polioptilidae",
          "genus": "Polioptila",
          "taxon_key": 2487596,
          "occurrences": 130
        },
        {
          "scientific_name": "Icterus pustulatus",
          "kingdom": "Animalia",
          "phylum": "Chordata",
          "class": "Aves",
          "order": "Passeriformes",
          "family": "Icteridae",
          "genus": "Icterus",
          "taxon_key": 5229853,
          "occurrences": 128
        },
        {
          "scientific_name": "Larus heermanni",
          "kingdom": "Animalia",
          "phylum": "Chordata",
          "class": "Aves",
          "order": "Charadriiformes",
          "family": "Laridae",
          "genus": "Larus",
          "taxon_key": 2481130,
          "occurrences": 125
        },
        {
          "scientific_name": "Setophaga petechia",
          "kingdom": "Animalia",
          "phylum": "Chordata",
          "class": "Aves",
          "order": "Passeriformes",
          "family": "Parulidae",
          "genus": "Setophaga",
          "taxon_key": 7341834,
          "occurrences": 121
        },
        {
          "scientific_name": "Dendrocygna autumnalis",
          "kingdom": "Animalia",
          "phylum": "Chordata",
          "class": "Aves",
          "order": "Anseriformes",
          "family": "Anatidae",
          "genus": "Dendrocygna",
          "taxon_key": 2498393,
          "occurrences": 121
        },
        {
          "scientific_name": "Streptopelia decaocto",
          "kingdom": "Animalia",
          "phylum": "Chordata",
          "class": "Aves",
          "order": "Columbiformes",
          "family": "Columbidae",
          "genus": "Streptopelia",
          "taxon_key": 2495696,
          "occurrences": 118
        },
        {
          "scientific_name": "Tringa semipalmata",
          "kingdom": "Animalia",
          "phylum": "Chordata",
          "class": "Aves",
          "order": "Charadriiformes",
          "family": "Scolopacidae",
          "genus": "Tringa",
          "taxon_key": 5789298,
          "occurrences": 109
        },
        {
          "scientific_name": "Jacana spinosa",
          "kingdom": "Animalia",
          "phylum": "Chordata",
          "class": "Aves",
          "order": "Charadriiformes",
          "family": "Jacanidae",
          "genus": "Jacana",
          "taxon_key": 9520263,
          "occurrences": 109
        },
        {
          "scientific_name": "Pheugopedius felix",
          "kingdom": "Animalia",
          "phylum": "Chordata",
          "class": "Aves",
          "order": "Passeriformes",
          "family": "Troglodytidae",
          "genus": "Pheugopedius",
          "taxon_key": 7341114,
          "occurrences": 104
        },
        {
          "scientific_name": "Myiozetetes similis",
          "kingdom": "Animalia",
          "phylum": "Chordata",
          "class": "Aves",
          "order": "Passeriformes",
          "family": "Tyrannidae",
          "genus": "Myiozetetes",
          "taxon_key": 2482913,
          "occurrences": 102
        },
        {
          "scientific_name": "Egretta tricolor",
          "kingdom": "Animalia",
          "phylum": "Chordata",
          "class": "Aves",
          "order": "Pelecaniformes",
          "family": "Ardeidae",
          "genus": "Egretta",
          "taxon_key": 2480881,
          "occurrences": 101
        },
        {
          "scientific_name": "Thalasseus maximus",
          "kingdom": "Animalia",
          "phylum": "Chordata",
          "class": "Aves",
          "order": "Charadriiformes",
          "family": "Laridae",
          "genus": "Thalasseus",
          "taxon_key": 5789281,
          "occurrences": 100
        },
        {
          "scientific_name": "Actitis macularius",
          "kingdom": "Animalia",
          "phylum": "Chordata",
          "class": "Aves",
          "order": "Charadriiformes",
          "family": "Scolopacidae",
          "genus": "Actitis",
          "taxon_key": 2481798,
          "occurrences": 100
        },
        {
          "scientific_name": "Leucophaeus atricilla",
          "kingdom": "Animalia",
          "phylum": "Chordata",
          "class": "Aves",
          "order": "Charadriiformes",
          "family": "Laridae",
          "genus": "Leucophaeus",
          "taxon_key": 6065844,
          "occurrences": 99
        },
        {
          "scientific_name": "Thryophilus sinaloa",
          "kingdom": "Animalia",
          "phylum": "Chordata",
          "class": "Aves",
          "order": "Passeriformes",
          "family": "Troglodytidae",
          "genus": "Thryophilus",
          "taxon_key": 7341103,
          "occurrences": 92
        },
        {
          "scientific_name": "Platalea ajaja",
          "kingdom": "Animalia",
          "phylum": "Chordata",
          "class": "Aves",
          "order": "Pelecaniformes",
          "family": "Threskiornithidae",
          "genus": "Platalea",
          "taxon_key": 2480803,
          "occurrences": 90
        },
        {
          "scientific_name": "Pyrocephalus rubinus",
          "kingdom": "Animalia",
          "phylum": "Chordata",
          "class": "Aves",
          "order": "Passeriformes",
          "family": "Tyrannidae",
          "genus": "Pyrocephalus",
          "taxon_key": 2483647,
          "occurrences": 89
        },
        {
          "scientific_name": "Mimus polyglottos",
          "kingdom": "Animalia",
          "phylum": "Chordata",
          "class": "Aves",
          "order": "Passeriformes",
          "family": "Mimidae",
          "genus": "Mimus",
          "taxon_key": 5231677,
          "occurrences": 87
        },
        {
          "scientific_name": "Columbina passerina",
          "kingdom": "Animalia",
          "phylum": "Chordata",
          "class": "Aves",
          "order": "Columbiformes",
          "family": "Columbidae",
          "genus": "Columbina",
          "taxon_key": 2495869,
          "occurrences": 84
        },
        {
          "scientific_name": "Cyanocorax sanblasianus",
          "kingdom": "Animalia",
          "phylum": "Chordata",
          "class": "Aves",
          "order": "Passeriformes",
          "family": "Corvidae",
          "genus": "Cyanocorax",
          "taxon_key": 2482578,
          "occurrences": 84
        },
        {
          "scientific_name": "Saltator grandis",
          "kingdom": "Animalia",
          "phylum": "Chordata",
          "class": "Aves",
          "order": "Passeriformes",
          "family": "Thraupidae",
          "genus": "Saltator",
          "taxon_key": 9126320,
          "occurrences": 83
        },
        {
          "scientific_name": "Ortalis poliocephala",
          "kingdom": "Animalia",
          "phylum": "Chordata",
          "class": "Aves",
          "order": "Galliformes",
          "family": "Cracidae",
          "genus": "Ortalis",
          "taxon_key": 5229451,
          "occurrences": 82
        },
        {
          "scientific_name": "Haematopus palliatus",
          "kingdom": "Animalia",
          "phylum": "Chordata",
          "class": "Aves",
          "order": "Charadriiformes",
          "family": "Haematopodidae",
          "genus": "Haematopus",
          "taxon_key": 2480273,
          "occurrences": 82
        },
        {
          "scientific_name": "Calidris minutilla",
          "kingdom": "Animalia",
          "phylum": "Chordata",
          "class": "Aves",
          "order": "Charadriiformes",
          "family": "Scolopacidae",
          "genus": "Calidris",
          "taxon_key": 2481745,
          "occurrences": 79
        },
        {
          "scientific_name": "Passer domesticus",
          "kingdom": "Animalia",
          "phylum": "Chordata",
          "class": "Aves",
          "order": "Passeriformes",
          "family": "Passeridae",
          "genus": "Passer",
          "taxon_key": 5231190,
          "occurrences": 79
        },
        {
          "scientific_name": "Sporophila torqueola",
          "kingdom": "Animalia",
          "phylum": "Chordata",
          "class": "Aves",
          "order": "Passeriformes",
          "family": "Thraupidae",
          "genus": "Sporophila",
          "taxon_key": 2491343,
          "occurrences": 79
        },
        {
          "scientific_name": "Spatula clypeata",
          "kingdom": "Animalia",
          "phylum": "Chordata",
          "class": "Aves",
          "order": "Anseriformes",
          "family": "Anatidae",
          "genus": "Spatula",
          "taxon_key": 8332393,
          "occurrences": 76
        },
        {
          "scientific_name": "Leiothlypis ruficapilla",
          "kingdom": "Animalia",
          "phylum": "Chordata",
          "class": "Aves",
          "order": "Passeriformes",
          "family": "Parulidae",
          "genus": "Leiothlypis",
          "taxon_key": 7531611,
          "occurrences": 74
        }
      ]
    },
    "iucn_threatened": {
      "source": "GBIF IUCN Red List data",
      "critically_endangered": [
        "Dalbergia granadillo",
        "Cedrela odorata"
      ],
      "endangered": [
        "Amazona finschi",
        "Chelonia mydas",
        "Bursera palaciosii",
        "Pocillopora verrucosa",
        "Amphipterygium glaucum",
        "Bourreria rubra",
        "Achatocarpus gracilis",
        "Jatropha bullockii",
        "Bombus steindachneri",
        "Bursera vazquezyanesii",
        "Schaefferia frutescens",
        "Swietenia humilis",
        "Ateleia standleyana",
        "Bourreria superba",
        "Helietta lottiae",
        "Persea chamissonis",
        "Croton culiacanensis"
      ],
      "vulnerable": [
        "Lepidochelys olivacea",
        "Trachemys ornata",
        "Limnodromus griseus",
        "Tringa flavipes",
        "Pluvialis squatarola",
        "Limosa fedoa",
        "Ara militaris",
        "Crocodylus acutus",
        "Pseudobatos glaucostigmus",
        "Dermochelys coriacea",
        "Eupherusa ridgwayi"
      ],
      "total_threatened": 30
    },
    "simec_nom059": {
      "error": "ANP not found in SIMEC data"
    },
    "nom059_enciclovida": {
      "source": "NOM-059-SEMARNAT (via Enciclovida)",
      "endangered_P": [],
      "threatened_A": [],
      "special_protection_Pr": [],
      "probably_extinct_E": [],
      "total_nom059": 0,
      "species_checked": 50
    },
    "inegi_census": {
      "source": "INEGI Censo 2020 (ITER)",
      "localities_in_area": 109,
      "total_population": 17222,
      "female_population": 8279,
      "male_population": 8765,
      "female_percent": 48.1,
      "indigenous_speakers_3plus": 538,
      "indigenous_speakers_5plus": 495,
      "indigenous_households_pop": 681,
      "afromexican_population": 298,
      "population_60plus": 2265,
      "economically_active": 8508,
      "employed": 8481,
      "unemployed": 27,
      "illiterate_15plus": 962,
      "no_schooling_15plus": 1058,
      "post_basic_education_18plus": 2653,
      "avg_schooling_years": 6.6,
      "no_health_services": 2846,
      "with_health_services": 14183,
      "with_disability": 1359,
      "homes_dirt_floor": 182,
      "homes_no_electricity": 58,
      "homes_no_water": 157,
      "homes_no_drainage": 235,
      "homes_no_services": 19,
      "total_households": 4751,
      "female_headed_households": 1422,
      "sample_localities": [
        "Ipala",
        "Paulo",
        "Los Rastrojos",
        "Santa Cruz del Tuito",
        "Villa del Mar",
        "Tehuamixtle (Tehualmixtle)",
        "El Turco",
        "Peregrina de G\u00f3mez (La Boquita)",
        "Tepehuajillo",
        "El Toro"
      ]
    },
    "extracted_at": "2026-01-03T01:32:49.474938",
    "coneval_irs": {
      "source": "CONEVAL IRS 2020 (Indice de Rezago Social)",
      "data_available": true,
      "municipalities_count": 2,
      "total_population": 47256,
      "irs_weighted_mean": -0.4152,
      "irs_predominant_category": "Bajo",
      "irs_category_distribution": {
        "Bajo": 2
      },
      "municipalities": [
        {
          "name": "Tomatl\u00e1n",
          "state": "Jalisco",
          "population": 36316,
          "irs_index": -0.433,
          "irs_category": "Bajo",
          "national_rank": 1460
        },
        {
          "name": "Cabo Corrientes",
          "state": "Jalisco",
          "population": 10940,
          "irs_index": -0.3561,
          "irs_category": "Bajo",
          "national_rank": 1377
        }
      ],
      "interpretation": {
        "irs_index": "Social Lag Index: negative values = low lag (better conditions), positive = high lag (worse conditions)",
        "categories": "Muy bajo (best) \u2192 Bajo \u2192 Medio \u2192 Alto \u2192 Muy alto (worst)",
        "weighted_mean": "Population-weighted average across all municipalities intersecting ANP"
      },
      "extracted_at": "2026-01-03T11:22:01.043680"
    },
    "inaturalist": {
      "source": "iNaturalist (Naturalista)",
      "data_available": true,
      "total_observations": 1108,
      "unique_species": 446,
      "species_by_group": {
        "Reptilia": 42,
        "Aves": 161,
        "Animalia": 18,
        "Plantae": 108,
        "Arachnida": 12,
        "Amphibia": 8,
        "Mollusca": 6,
        "Mammalia": 14,
        "Insecta": 57,
        "Actinopterygii": 14,
        "Fungi": 6
      },
      "top_species": [
        {
          "scientific_name": "Lepidochelys olivacea",
          "common_name": "Tortuga Golfina",
          "iconic_taxon": "Reptilia",
          "observations": 25,
          "taxon_id": 39670
        },
        {
          "scientific_name": "Pelecanus occidentalis",
          "common_name": "Pel\u00edcano caf\u00e9",
          "iconic_taxon": "Aves",
          "observations": 23,
          "taxon_id": 4328
        },
        {
          "scientific_name": "Ctenosaura pectinata",
          "common_name": "Iguana mexicana de cola espinosa",
          "iconic_taxon": "Reptilia",
          "observations": 17,
          "taxon_id": 35306
        },
        {
          "scientific_name": "Caracara plancus",
          "common_name": "Carancho",
          "iconic_taxon": "Aves",
          "observations": 16,
          "taxon_id": 4715
        },
        {
          "scientific_name": "Melanerpes chrysogenys",
          "common_name": "Carpintero enmascarado",
          "iconic_taxon": "Aves",
          "observations": 14,
          "taxon_id": 18206
        },
        {
          "scientific_name": "Eupsittula canicularis",
          "common_name": "Perico frente naranja",
          "iconic_taxon": "Aves",
          "observations": 14,
          "taxon_id": 367558
        },
        {
          "scientific_name": "Passerina leclancherii",
          "common_name": "Color\u00ed\u00adn pecho naranja",
          "iconic_taxon": "Aves",
          "observations": 12,
          "taxon_id": 10232
        },
        {
          "scientific_name": "Eudocimus albus",
          "common_name": "Ibis Blanco",
          "iconic_taxon": "Aves",
          "observations": 11,
          "taxon_id": 3751
        },
        {
          "scientific_name": "Fregata magnificens",
          "common_name": "Fragata Tijereta",
          "iconic_taxon": "Aves",
          "observations": 11,
          "taxon_id": 4631
        },
        {
          "scientific_name": "Nyctanassa violacea",
          "common_name": "Garza Nocturna Corona Clara",
          "iconic_taxon": "Aves",
          "observations": 11,
          "taxon_id": 4999
        },
        {
          "scientific_name": "Tyrannus melancholicus",
          "common_name": "Tirano Pirir\u00ed",
          "iconic_taxon": "Aves",
          "observations": 11,
          "taxon_id": 16787
        },
        {
          "scientific_name": "Grapsus grapsus",
          "common_name": "Zapaya",
          "iconic_taxon": "Animalia",
          "observations": 11,
          "taxon_id": 55295
        },
        {
          "scientific_name": "Mammillaria beiselii",
          "common_name": null,
          "iconic_taxon": "Plantae",
          "observations": 11,
          "taxon_id": 564376
        },
        {
          "scientific_name": "Cathartes aura",
          "common_name": "Zopilote aura",
          "iconic_taxon": "Aves",
          "observations": 10,
          "taxon_id": 4756
        },
        {
          "scientific_name": "Haematopus palliatus",
          "common_name": "Ostrero Americano",
          "iconic_taxon": "Aves",
          "observations": 10,
          "taxon_id": 4840
        },
        {
          "scientific_name": "Ardea alba",
          "common_name": "Garza blanca",
          "iconic_taxon": "Aves",
          "observations": 10,
          "taxon_id": 144455
        },
        {
          "scientific_name": "Buteo plagiatus",
          "common_name": "Aguililla gris",
          "iconic_taxon": "Aves",
          "observations": 10,
          "taxon_id": 199913
        },
        {
          "scientific_name": "Egretta thula",
          "common_name": "Garza dedos dorados",
          "iconic_taxon": "Aves",
          "observations": 9,
          "taxon_id": 4940
        },
        {
          "scientific_name": "Platalea ajaja",
          "common_name": "Esp\u00e1tula rosada",
          "iconic_taxon": "Aves",
          "observations": 9,
          "taxon_id": 62529
        },
        {
          "scientific_name": "Nannopterum brasilianum",
          "common_name": "Cor\u00faa Neotropical",
          "iconic_taxon": "Aves",
          "observations": 9,
          "taxon_id": 1289601
        },
        {
          "scientific_name": "Fulica americana",
          "common_name": "Gallareta americana",
          "iconic_taxon": "Aves",
          "observations": 8,
          "taxon_id": 473
        },
        {
          "scientific_name": "Larus heermanni",
          "common_name": "Gaviota Plomiza",
          "iconic_taxon": "Aves",
          "observations": 8,
          "taxon_id": 4353
        },
        {
          "scientific_name": "Ara militaris",
          "common_name": "Guacamaya verde",
          "iconic_taxon": "Aves",
          "observations": 8,
          "taxon_id": 19020
        },
        {
          "scientific_name": "Trogon citreolus",
          "common_name": "Coa Citrina",
          "iconic_taxon": "Aves",
          "observations": 8,
          "taxon_id": 20787
        },
        {
          "scientific_name": "Iguana iguana",
          "common_name": "Iguana verde",
          "iconic_taxon": "Reptilia",
          "observations": 8,
          "taxon_id": 35342
        },
        {
          "scientific_name": "Rupornis magnirostris",
          "common_name": "Aguililla caminera",
          "iconic_taxon": "Aves",
          "observations": 8,
          "taxon_id": 201041
        },
        {
          "scientific_name": "Crotophaga sulcirostris",
          "common_name": "Garrapatero pijuy",
          "iconic_taxon": "Aves",
          "observations": 7,
          "taxon_id": 1972
        },
        {
          "scientific_name": "Coragyps atratus",
          "common_name": "Zopilote com\u00fan",
          "iconic_taxon": "Aves",
          "observations": 7,
          "taxon_id": 4765
        },
        {
          "scientific_name": "Egretta caerulea",
          "common_name": "Garceta Azul",
          "iconic_taxon": "Aves",
          "observations": 7,
          "taxon_id": 4937
        },
        {
          "scientific_name": "Ardea herodias",
          "common_name": "Garza morena",
          "iconic_taxon": "Aves",
          "observations": 7,
          "taxon_id": 4956
        }
      ],
      "bounding_box": {
        "minLon": -105.58197488876448,
        "maxLon": -105.24700282995568,
        "minLat": 19.669576298531243,
        "maxLat": 20.239266596551072
      },
      "quality_filter": "research-grade only",
      "interpretation": {
        "observations": "Total research-grade observations in area",
        "species": "Unique species identified by community",
        "note": "Citizen science data - effort varies by accessibility"
      },
      "extracted_at": "2026-01-03T11:52:39.090062"
    }
  }
}